redismirror/__init__.py
redismirror/main.py
redismirror-1.0.1.dist-info/LICENSE
redismirror-1.0.1.dist-info/METADATA
redismirror-1.0.1.dist-info/WHEEL
redismirror-1.0.1.dist-info/entry_points.txt
redismirror-1.0.1.dist-info/top_level.txt
redismirror-1.0.1.dist-info/RECORD
