Metadata-Version: 2.1
Name: redismirror
Version: 1.0.1
Summary: Mirror Redis Traffic to another redis node
Home-page: https://github.com/alivx/redis-mirror
Author: Ali Saleh Baker
Author-email: alivxlive@gmail.com
License: MIT
Keywords: traffic,mirror,redis,migration,cli
Platform: UNKNOWN
Requires-Dist: redis (==4.5.1)
Requires-Dist: click (==8.1.3)
Requires-Dist: tqdm (==4.65.0)
